<?xml version="1.0" ?>
<annotation>
	<folder>MuchPeople</folder>
	<filename>1</filename>
	<path>E:\LocalProject\FaceAnnotationTool\MuchPeople\1.jpg</path>
	<source>
		<database>Unknown</database>
	</source>
	<size>
		<width>2048</width>
		<height>1217</height>
		<depth>3</depth>
	</size>
	<segmented>0</segmented>
	<object>
		<name>face</name>
		<pose>Unspecified</pose>
		<truncated>0</truncated>
		<difficult>0</difficult>
		<bndbox>
			<x>790</x>
			<y>364</y>
			<width>143</width>
			<height>143</height>
		</bndbox>
	</object>
</annotation>
